CHANGELOG.txt
Licence.txt
MANIFEST.in
README.txt
setup.py
ahnufBasicCalc/__init__.py
ahnufbasiccalculator.egg-info/SOURCES.txt
ahnufbasiccalculator.egg-info/dependency_links.txt
ahnufbasiccalculator.egg-info/top_level.txt
ahnufcalc.egg-info/PKG-INFO
ahnufcalc.egg-info/SOURCES.txt
ahnufcalc.egg-info/dependency_links.txt
ahnufcalc.egg-info/top_level.txt